{"body":"TEST EDIT OpenRefine is a power tool that allows you to load data, understand it, clean it up, reconcile it internally, and augment it with data coming from Freebase or other web sources. All with the comfort and privacy of your own computer.  You can find more information at http://github.com/OpenRefine/OpenRefine\r\n\r\n###Licensing\r\n\r\nOpenRefine is open source software and is licensed under the BSD license\r\nlocated in the LICENSE.txt. See that file also for information on open source\r\nlibraries that  depends on.\r\n\r\n###Credits\r\n\r\nThis software was created by Metaweb Technologies, Inc. and originally written\r\nand conceived by David Huynh <dfhuynh@google.com>. Metaweb Technologies, Inc.\r\nwas acquired by Google, Inc. in July 2010 and the product was renamed Google Refine.\r\nIn October 2012, it was renamed OpenRefine as it transitioned to a \r\ncommunity-supported product.\r\n\r\nThis is the full list of contributors (in chronological order):\r\n\r\n - David Huynh <dfhuynh@google.com>\r\n - Stefano Mazzocchi <stefanom@google.com>\r\n - Vishal Talwar <vtalwar@google.com> \r\n - Jeff Fry <jfry@google.com>\r\n - Will Moffat <wdm@google.com>\r\n - James Home <jameshome@google.com>\r\n - Iain Sproat <iainsproat@gmail.com>\r\n - Tom Morris <tfmorris@gmail.com>\r\n - Heather Campbell <campbellh@google.com>\r\n - Thad Guidry <thadguidry@gmail.com>\r\n - Paul Makepeace <paulm@paulm.com>\r\n - Tomaž Šolc <tomaz.solc@zemanta.com>\r\n - Gabriel Sjoberg <GabrielSjoberg@gmail.com>\r\n - Rod Salazar <rodrod.salazar@gmail.com>\r\n - pxb <pxb1988@gmail.com>\r\n \r\n We welcome additional contributors if you'd like to help out.\r\n\r\n                                        ","google":"UA-35838111-1","note":"Don't delete this file! It's used internally to help with page regeneration.","tagline":"A free, open source, power tool for working with messy data","name":"OpenRefine"}